hackmd/__init__.py
hackmd/__version__.py
hackmd/client.py
hackmd_sdk_python-0.2.1.dist-info/LICENSE
hackmd_sdk_python-0.2.1.dist-info/METADATA
hackmd_sdk_python-0.2.1.dist-info/WHEEL
hackmd_sdk_python-0.2.1.dist-info/top_level.txt
hackmd_sdk_python-0.2.1.dist-info/RECORD
