Metadata-Version: 2.1
Name: hackmd-sdk-python
Version: 0.2.1
Summary: Type-safe python SDK for HackMD developer
Home-page: https://github.com/louis70109/hackmd-sdk-python
Author: NiJia Lin
Author-email: louis70109@gmail.com
Maintainer: NiJia Lin
Maintainer-email: louis70109@gmail.com
License: MIT
Project-URL: Bug Reports, https://github.com/louis70109/hackmd-sdk-python/issues
Project-URL: Source, https://github.com/louis70109/hackmd-sdk-python
Keywords: Hackmd
Classifier: Development Status :: 5 - Production/Stable
Classifier: License :: OSI Approved :: MIT License
Classifier: Intended Audience :: Developers
Classifier: Programming Language :: Python
Classifier: Programming Language :: Python :: 3
Classifier: Programming Language :: Python :: 3.7
Classifier: Programming Language :: Python :: 3.8
Classifier: Programming Language :: Python :: 3.9
Classifier: Programming Language :: Python :: 3.10
Classifier: Topic :: Software Development
Requires-Python: !=3.0.*, !=3.1.*, !=3.2.*, !=3.3.*, !=3.4.*
License-File: LICENSE
Requires-Dist: requests (>=2.0)
